gprof2dot_magic.py
gprof2dot_magic-0.4.dist-info/LICENSE
gprof2dot_magic-0.4.dist-info/WHEEL
gprof2dot_magic-0.4.dist-info/METADATA
gprof2dot_magic-0.4.dist-info/RECORD
